airpy/__init__.py
airpy/cli.py
airpy/core/__init__.py
airpy/core/file_processor.py
airpy/core/processor.py
airpy/data/__init__.py
airpy/data/sites_master.csv
airpy/utils/__init__.py
airpy/utils/cleaning.py
airpy/utils/formatting.py
airpy/utils/metadata.py
airpy_tool-2.0.0.dist-info/licenses/LICENSE
airpy_tool-2.0.0.dist-info/METADATA
airpy_tool-2.0.0.dist-info/WHEEL
airpy_tool-2.0.0.dist-info/entry_points.txt
airpy_tool-2.0.0.dist-info/top_level.txt
airpy_tool-2.0.0.dist-info/RECORD
