Metadata-Version: 2.4
Name: airpy-tool
Version: 2.0.0
Summary: A tool for cleaning and processing CPCB air quality data
Home-page: https://github.com/chandankr014/airpy-tool
Author: Chandan Kumar
Author-email: Chandan Kumar <chandankr014@gmail.com>
License: MIT License
Project-URL: Homepage, https://github.com/chandankr014/airpy-tool
Project-URL: Bug Tracker, https://github.com/chandankr014/airpy-tool/issues
Classifier: Programming Language :: Python :: 3
Classifier: License :: OSI Approved :: MIT License
Classifier: Operating System :: OS Independent
Classifier: Topic :: Scientific/Engineering :: Atmospheric Science
Requires-Python: >=3.6
License-File: LICENSE
Requires-Dist: pandas
Requires-Dist: numpy
Dynamic: author
Dynamic: home-page
Dynamic: license-file
Dynamic: requires-python
